MANIFEST.in
README.rst
addmedia-deluge
setup.py
docs/Makefile
docs/conf.py
docs/index.rst
docs/configuration/commandline.rst
docs/configuration/deluge.rst
docs/configuration/example.rst
docs/configuration/index.rst
docs/configuration/requirements.rst
docs/configuration/settings.rst
docs/development/handler.rst
docs/development/index.rst
docs/development/object.rst
docs/development/types-audiobooks.rst
docs/development/types-movies.rst
docs/development/types-music.rst
docs/development/types-tv.rst
docs/development/types.rst
docs/development/util-args.rst
docs/development/util-config.rst
docs/development/util-extract.rst
docs/development/util-notify.rst
docs/development/util-torrent.rst
docs/development/util.rst
docs/guide/index.rst
em_media_handler.egg-info/PKG-INFO
em_media_handler.egg-info/SOURCES.txt
em_media_handler.egg-info/dependency_links.txt
em_media_handler.egg-info/entry_points.txt
em_media_handler.egg-info/pbr.json
em_media_handler.egg-info/requires.txt
em_media_handler.egg-info/top_level.txt
mediahandler/__init__.py
mediahandler/handler.py
mediahandler/extras/blacklist.txt
mediahandler/extras/config.yml
mediahandler/extras/require.yml
mediahandler/extras/settings.yml
mediahandler/types/__init__.py
mediahandler/types/audiobooks.py
mediahandler/types/movies.py
mediahandler/types/music.py
mediahandler/types/tv.py
mediahandler/util/__init__.py
mediahandler/util/args.py
mediahandler/util/config.py
mediahandler/util/extract.py
mediahandler/util/notify.py
mediahandler/util/torrent.py
tests/__init__.py
tests/_common.py
tests/test_args.py
tests/test_books.py
tests/test_config.py
tests/test_extract.py
tests/test_handler.py
tests/test_media.py
tests/test_movies.py
tests/test_music.py
tests/test_notify.py
tests/test_torrent.py
tests/test_tv.py
tests/testall.py