Metadata-Version: 1.0
Name: em-media-handler
Version: 1.0b3
Summary: A comprehensive media handling automation script.
Home-page: http://erinmorelli.com/projects/em-media-handler/
Author: Erin Morelli
Author-email: erin@erinmorelli.com
License: MIT
Platform: Linux
Platform: OSX
Classifier: Topic :: Home Automation
Classifier: Topic :: Multimedia
Classifier: Topic :: Software Development :: Libraries :: Python Modules
Classifier: License :: OSI Approved :: MIT License
Classifier: Environment :: MacOS X
Classifier: Environment :: Console
Classifier: Programming Language :: Python
Classifier: Programming Language :: Python :: 2.6
Classifier: Programming Language :: Python :: 2.7
Classifier: Operating System :: MacOS
Classifier: Operating System :: POSIX :: Linux
